tracematrix/item.py
tracematrix/matrix.py
tracematrix/reporters/__init__.py
tracematrix/reporters/base_reporter.py
tracematrix/reporters/csv_reporter.py
tracematrix/reporters/html_reporter.py
tracematrix/reporters/template.html
tracematrix-1.0.1.dist-info/LICENSE
tracematrix-1.0.1.dist-info/WHEEL
tracematrix-1.0.1.dist-info/METADATA
tracematrix-1.0.1.dist-info/RECORD
