Metadata-Version: 2.1
Name: tracematrix
Version: 1.0.1
Summary: Tool to create a traceability matrix
Home-page: https://github.com/DudeNr33/tracematrix
License: MIT
Keywords: requirements,traceability,testing,requirements engineering
Author: Andreas Finkler
Requires-Python: >=3.6.2,<4.0.0
Classifier: Development Status :: 4 - Beta
Classifier: License :: OSI Approved :: MIT License
Classifier: Programming Language :: Python :: 3
Classifier: Programming Language :: Python :: 3.7
Classifier: Programming Language :: Python :: 3.8
Classifier: Programming Language :: Python :: 3.9
Classifier: Topic :: Software Development
Classifier: Topic :: Software Development :: Quality Assurance
Classifier: Topic :: Software Development :: Testing
Requires-Dist: Jinja2 (>=3.0.1,<4.0.0)
